hello_world_vis/__init__.py
hello_world_vis/hello.py
hello_world_vis-0.1.dist-info/METADATA
hello_world_vis-0.1.dist-info/WHEEL
hello_world_vis-0.1.dist-info/top_level.txt
hello_world_vis-0.1.dist-info/RECORD
