Metadata-Version: 2.1
Name: hello-world-vis
Version: 0.1
Summary: purpose of this package is demonstration
Home-page: https://github.com/VishvajeetRamanuj/hello_world_package
Author: UNKNOWN
Author-email: vishvajeetramanuj95@gmail.com
License: MIT
Platform: UNKNOWN
